Metadata-Version: 1.0
Name: QuartzFramework
Version: 0.4
Summary: An Exploitation Framework
Home-page: UNKNOWN
Author: QuartzSec
Author-email: ydku@quartz.ai
License: UNKNOWN
Platform: UNKNOWN
